opencv_gst_rtmp/__init__.py
opencv_gst_rtmp/base/__init__.py
opencv_gst_rtmp/base/gst_base.py
opencv_gst_rtmp/base/opencv_gst_rtmp.py
opencv_gst_rtmp/config/__init__.py
opencv_gst_rtmp/config/config.py
opencv_gst_rtmp/config/logging_config.py
opencv_gst_rtmp/config/logging_formatter.py
opencv_gst_rtmp/exception/__init__.py
opencv_gst_rtmp/exception/element_exception.py
opencv_gst_rtmp/exception/network_exception.py
opencv_gst_rtmp/implement/__init__.py
opencv_gst_rtmp/implement/opencv_frame_gst_rtmp.py
opencv_gst_rtmp/implement/opencv_stream_gst_rtmp.py
opencv_gst_rtmp/utils/__init__.py
opencv_gst_rtmp/utils/gst_utils.py
opencv_gst_rtmp/utils/thread_utils.py
opencv_gst_rtmp-0.1.1.dist-info/licenses/LICENSE.txt
opencv_gst_rtmp-0.1.1.dist-info/METADATA
opencv_gst_rtmp-0.1.1.dist-info/WHEEL
opencv_gst_rtmp-0.1.1.dist-info/top_level.txt
opencv_gst_rtmp-0.1.1.dist-info/RECORD
