Metadata-Version: 2.4
Name: opencv_gst_rtmp
Version: 0.1.1
Summary: Push opencv frame to rtmp server using gstreamer
Home-page: https://github.com/nguyencobap/opencv_gst_rtmp
Author: Nguyen Hai Nguyen
Author-email: nguyenhainguyen97@gmail.com
License: MIT License
Keywords: gstreamer,gst,opencv,rtmp
Classifier: Development Status :: 5 - Production/Stable
Classifier: Intended Audience :: Developers
Classifier: Topic :: Multimedia :: Video
Classifier: License :: OSI Approved :: MIT License
Classifier: Operating System :: POSIX :: Linux
Classifier: Programming Language :: Python :: 3.8
Requires-Python: >=3.5
License-File: LICENSE.txt
Requires-Dist: opencv-python>=4.6.0.66
Requires-Dist: pycairo>=1.20.1
Requires-Dist: PyGObject>=3.42.2
Dynamic: author
Dynamic: author-email
Dynamic: classifier
Dynamic: description
Dynamic: description-content-type
Dynamic: home-page
Dynamic: keywords
Dynamic: license
Dynamic: license-file
Dynamic: requires-dist
Dynamic: requires-python
Dynamic: summary
